lida/__init__.py
lida/cli.py
lida/datamodel.py
lida/utils.py
lida/version.py
lida/components/__init__.py
lida/components/executor.py
lida/components/goal.py
lida/components/infographer.py
lida/components/manager.py
lida/components/persona.py
lida/components/scaffold.py
lida/components/summarizer.py
lida/components/viz/__init__.py
lida/components/viz/vizeditor.py
lida/components/viz/vizevaluator.py
lida/components/viz/vizexplainer.py
lida/components/viz/vizgenerator.py
lida/components/viz/vizrecommender.py
lida/components/viz/vizrepairer.py
lida/web/.gitignore
lida/web/__init__.py
lida/web/app.py
lida/web/ui/21614df092a0a42959abd49fa5ffec5702fa9463-ea1bf954f60f23d1e6a7.js
lida/web/ui/21614df092a0a42959abd49fa5ffec5702fa9463-ea1bf954f60f23d1e6a7.js.map
lida/web/ui/404.html
lida/web/ui/81e257386408544e35976acc2a4075b730ed48a4-326068d326429305ec9e.js
lida/web/ui/81e257386408544e35976acc2a4075b730ed48a4-326068d326429305ec9e.js.LICENSE.txt
lida/web/ui/81e257386408544e35976acc2a4075b730ed48a4-326068d326429305ec9e.js.map
lida/web/ui/app-80dcacffbc4d71399cc7.js
lida/web/ui/app-80dcacffbc4d71399cc7.js.map
lida/web/ui/chunk-map.json
lida/web/ui/component---src-pages-404-tsx-271998ff555bf33bd7ce.js
lida/web/ui/component---src-pages-404-tsx-271998ff555bf33bd7ce.js.map
lida/web/ui/component---src-pages-demo-tsx-54fd6da10fa870d8d843.js
lida/web/ui/component---src-pages-demo-tsx-54fd6da10fa870d8d843.js.LICENSE.txt
lida/web/ui/component---src-pages-demo-tsx-54fd6da10fa870d8d843.js.map
lida/web/ui/component---src-pages-index-tsx-36a4bd360cacad51120f.js
lida/web/ui/component---src-pages-index-tsx-36a4bd360cacad51120f.js.LICENSE.txt
lida/web/ui/component---src-pages-index-tsx-36a4bd360cacad51120f.js.map
lida/web/ui/component---src-pages-login-tsx-bbe1cb64566ee588bf48.js
lida/web/ui/component---src-pages-login-tsx-bbe1cb64566ee588bf48.js.map
lida/web/ui/favicon-32x32.png
lida/web/ui/framework-adcf09f5896f386aa38b.js
lida/web/ui/framework-adcf09f5896f386aa38b.js.LICENSE.txt
lida-0.0.14.dist-info/LICENSE
lida-0.0.14.dist-info/METADATA
lida-0.0.14.dist-info/WHEEL
lida-0.0.14.dist-info/entry_points.txt
lida-0.0.14.dist-info/top_level.txt
lida-0.0.14.dist-info/RECORD
