Metadata-Version: 2.1
Name: lida
Version: 0.0.14
Summary: LIDA: Automatic Generation of Visualizations from Data
Author-email: Victor Dibia <victordibia@microsoft.com>
License:     MIT License
Project-URL: Homepage, https://github.com/microsoft/lida
Project-URL: Bug Tracker, https://github.com/microsoft/lida/issues
Classifier: Programming Language :: Python :: 3
Classifier: License :: OSI Approved :: MIT License
Classifier: Operating System :: OS Independent
Requires-Python: >=3.9
License-File: LICENSE
Requires-Dist: llmx>=0.0.21a
Requires-Dist: pydantic
Requires-Dist: uvicorn
Requires-Dist: typer
Requires-Dist: fastapi
Requires-Dist: python-multipart
Requires-Dist: scipy
Requires-Dist: numpy
Requires-Dist: pandas
Requires-Dist: matplotlib
Requires-Dist: altair
Requires-Dist: seaborn
Requires-Dist: plotly
Requires-Dist: plotnine
Requires-Dist: statsmodels
Requires-Dist: networkx
Requires-Dist: geopandas
Requires-Dist: matplotlib-venn
Requires-Dist: wordcloud
Requires-Dist: kaleido!=0.2.1.post1,>=0.2.1
Provides-Extra: web
Requires-Dist: fastapi; extra == "web"
Requires-Dist: uvicorn; extra == "web"
Provides-Extra: transformers
Requires-Dist: llmx[transformers]; extra == "transformers"
Provides-Extra: tools
Requires-Dist: geopy; extra == "tools"
Requires-Dist: basemap; extra == "tools"
Requires-Dist: basemap-data-hires; extra == "tools"
Provides-Extra: infographics
Requires-Dist: peacasso; extra == "infographics"
